LICENSE
MANIFEST.in
README.md
setup.py
dev/requirements.txt
pypaimon/__init__.py
pypaimon.egg-info/PKG-INFO
pypaimon.egg-info/SOURCES.txt
pypaimon.egg-info/dependency_links.txt
pypaimon.egg-info/requires.txt
pypaimon.egg-info/top_level.txt
pypaimon/api/__init__.py
pypaimon/api/api_request.py
pypaimon/api/api_response.py
pypaimon/api/auth.py
pypaimon/api/client.py
pypaimon/api/options.py
pypaimon/api/resource_paths.py
pypaimon/api/rest_api.py
pypaimon/api/rest_exception.py
pypaimon/api/rest_util.py
pypaimon/api/token_loader.py
pypaimon/api/typedef.py
pypaimon/catalog/__init__.py
pypaimon/catalog/catalog.py
pypaimon/catalog/catalog_context.py
pypaimon/catalog/catalog_environment.py
pypaimon/catalog/catalog_exception.py
pypaimon/catalog/catalog_factory.py
pypaimon/catalog/catalog_loader.py
pypaimon/catalog/database.py
pypaimon/catalog/filesystem_catalog.py
pypaimon/catalog/rest/__init__.py
pypaimon/catalog/rest/property_change.py
pypaimon/catalog/rest/rest_catalog.py
pypaimon/catalog/rest/rest_catalog_loader.py
pypaimon/catalog/rest/rest_token.py
pypaimon/catalog/rest/rest_token_file_io.py
pypaimon/catalog/rest/table_metadata.py
pypaimon/common/__init__.py
pypaimon/common/config.py
pypaimon/common/core_options.py
pypaimon/common/delta_varint_compressor.py
pypaimon/common/file_io.py
pypaimon/common/identifier.py
pypaimon/common/json_util.py
pypaimon/common/predicate.py
pypaimon/common/predicate_builder.py
pypaimon/common/uri_reader.py
pypaimon/filesystem/__init__.py
pypaimon/filesystem/pvfs.py
pypaimon/manifest/__init__.py
pypaimon/manifest/manifest_file_manager.py
pypaimon/manifest/manifest_list_manager.py
pypaimon/manifest/simple_stats_evolution.py
pypaimon/manifest/simple_stats_evolutions.py
pypaimon/manifest/schema/__init__.py
pypaimon/manifest/schema/data_file_meta.py
pypaimon/manifest/schema/manifest_entry.py
pypaimon/manifest/schema/manifest_file_meta.py
pypaimon/manifest/schema/simple_stats.py
pypaimon/read/__init__.py
pypaimon/read/interval_partition.py
pypaimon/read/partition_info.py
pypaimon/read/plan.py
pypaimon/read/push_down_utils.py
pypaimon/read/read_builder.py
pypaimon/read/split.py
